{
    "id": "101",
    "transform": {
        "translation": {
            "x": 162853.0087,
            "y": 103750.3332,
            "z": 18132.9574
        },
        "rotation": {
            "x": 0.0482,
            "y": -0.1049,
            "z": -0.9026,
            "w": 0.4146
        },
        "scale3D": {
            "x": 1.0,
            "y": 1.0,
            "z": 1.0
        }
    },
    "name": "圆型触发器（无特效）",
    "description": "null",
    "kinds": "null",
    "author": "jaeezhou",
    "version": "null",
    "source": "puzzle_initial_data@10002",
    "LuaID": 10002,
    "UE5": {
        "Radius": {
            "Type": "Float",
            "Value": 400.0
        },
        "UE5Comps": {
            "RootSphere": {
                "RelativeLocation": {
                    "Type": "Vector",
                    "Value": {
                        "x": 162853.0087,
                        "y": 103750.3332,
                        "z": 18132.9574
                    }
                }
            },
            "Sphere": {
                "SphereRadius": {
                    "Type": "Float",
                    "Value": 400.0
                }
            }
        }
    }
}