{
    "id": "1",
    "transform": {
        "translation": {
            "x": 166068.0,
            "y": 106181.0,
            "z": 18575.0
        },
        "rotation": {
            "x": 0.0,
            "y": 0.0,
            "z": 0.9962,
            "w": 0.0871
        },
        "scale3D": {
            "x": 1.0,
            "y": 1.0,
            "z": 1.0
        }
    },
    "name": "风向标",
    "description": "null",
    "kinds": "null",
    "author": "jaeezhou",
    "version": "null",
    "source": "puzzle_initial_data@20044",
    "LuaID": 20044,
    "UE5": {
        "UE5Comps": {
            "Box": {
                "CanCharacterClimbOn": {
                    "Type": "Enum@CanBeCharacterBase",
                    "Value": "ECB_NO@0"
                },
                "BodyInstance": {
                    "Type": "StructBase@BodyInstance",
                    "Value": "(ObjectType=ECC_WorldStatic,CollisionEnabled=NoCollision,SleepFamily=Normal,DOFMode=Default,bUseCCD=False,bIgnoreAnalyticCollisions=False,bNotifyRigidBodyCollision=False,bSmoothEdgeCollisions=False,bLockTranslation=True,bLockRotation=True,bLockXTranslation=False,bLockYTranslation=False,bLockZTranslation=False,bLockXRotation=False,bLockYRotation=False,bLockZRotation=False,bOverrideMaxAngularVelocity=False,bOverrideMaxDepenetrationVelocity=False,bOverrideWalkableSlopeOnInstance=False,bInterpolateWhenSubStepping=False,bInertiaConditioning=True,CollisionProfileName=\"Custom\",PositionSolverIterationCount=8,VelocitySolverIterationCount=1,CollisionResponses=(ResponseArray=((Channel=\"WorldStatic\",Response=ECR_Ignore),(Channel=\"WorldDynamic\",Response=ECR_Ignore),(Channel=\"Pawn\",Response=ECR_Ignore),(Channel=\"Visibility\",Response=ECR_Ignore),(Channel=\"Camera\",Response=ECR_Ignore),(Channel=\"PhysicsBody\",Response=ECR_Ignore),(Channel=\"Vehicle\",Response=ECR_Ignore),(Channel=\"Destructible\",Response=ECR_Ignore),(Channel=\"BossPawn\",Response=ECR_Ignore),(Channel=\"Weapon\",Response=ECR_Ignore),(Channel=\"Projectile\",Response=ECR_Ignore),(Channel=\"TrapActor\",Response=ECR_Ignore))),MaxDepenetrationVelocity=0.000000,MassInKgOverride=100.000000,LinearDamping=0.010000,AngularDamping=0.000000,CustomDOFPlaneNormal=(X=0.000000,Y=0.000000,Z=0.000000),COMNudge=(X=0.000000,Y=0.000000,Z=0.000000),MassScale=1.000000,InertiaTensorScale=(X=1.000000,Y=1.000000,Z=1.000000),WalkableSlopeOverride=(WalkableSlopeBehavior=WalkableSlope_Default,WalkableSlopeAngle=0.000000),PhysMaterialOverride=None,MaxAngularVelocity=3600.000000,CustomSleepThresholdMultiplier=1.000000,StabilizationThresholdMultiplier=1.000000,PhysicsBlendWeight=0.000000,bSimulatePhysics=False,bOverrideMass=False,bEnableGravity=True,bAutoWeld=True,bStartAwake=True,bGenerateWakeEvents=False,bUpdateMassWhenScaleChanges=True)"
                }
            },
            "RootSphere": {
                "RelativeLocation": {
                    "Type": "Vector",
                    "Value": {
                        "x": 166068.0,
                        "y": 106181.0,
                        "z": 18575.0
                    }
                }
            }
        }
    },
    "SuiteDir": "suite25"
}