{
    "id": "5",
    "transform": {
        "translation": {
            "x": 155372.2478,
            "y": 141562.0486,
            "z": 19439.1772
        },
        "rotation": {
            "x": 0.0,
            "y": 0.0,
            "z": 0.3292,
            "w": 0.9443
        },
        "scale3D": {
            "x": 1.0,
            "y": 1.0,
            "z": 1.0
        }
    },
    "name": "小男孩npc",
    "description": "null",
    "kinds": "null",
    "author": "jaeezhou",
    "version": "null",
    "source": "npc_base_data@300021",
    "LuaID": 300021,
    "SuiteDir": "suite26",
    "UE5": {
        "DisplayName": {
            "Type": "String",
            "Value": "伊凡"
        },
        "AutoSpawn": {
            "Type": "Boolean",
            "Value": true
        },
        "EditorTags": {
            "Type": "Array",
            "Value": [
                {
                    "Type": "String",
                    "Value": "40000"
                }
            ]
        },
        "ActorGuid": {
            "Type": "String",
            "Value": "7B6CA5C9411BFA507D99EC84DE60B345"
        },
        "UE5Comps": {
            "CharacterMesh0": {
                "AnimationData": {
                    "Type": "StructBase@SingleAnimationPlayData",
                    "Value": "(AnimToPlay=\"/Script/Engine.AnimSequence'/Game/Character/NPC/LittleBoy/Animation/LittleBoy_P_Stand.LittleBoy_P_Stand'\",bSavedLooping=True,bSavedPlaying=True,SavedPosition=0.000000,SavedPlayRate=1.000000)"
                },
                "AnimationMode": {
                    "Type": "Enum@AnimationMode",
                    "Value": "ANIMATION_SINGLE_NODE@1"
                }
            },
            "CollisionCylinder": {
                "RelativeLocation": {
                    "Type": "Vector",
                    "Value": {
                        "x": 155372.2478,
                        "y": 141562.0486,
                        "z": 19439.1772
                    }
                },
                "RelativeRotation": {
                    "Type": "StructBase@Rotator",
                    "Value": "(Pitch=0.000000,Yaw=38.438951,Roll=0.000000)"
                }
            },
            "DialogueComponent": {
                "DefaultInteractList": {
                    "Type": "Array",
                    "Value": [
                        {
                            "Type": "Int",
                            "Value": 11005
                        }
                    ]
                },
                "DefaultDialogueId": {
                    "Type": "Int",
                    "Value": 4000109
                }
            }
        }
    }
}