{
  "20058001": {
    "id": "20058001",
    "ShowId": "1001",
    "translation": {
      "x": -520.873,
      "y": -450.598,
      "z": 0
    }
  },
  "20059001": {
    "id": "20059001",
    "ShowId": "1002",
    "translation": {
      "x": -467.698,
      "y": -443.028,
      "z": 0
    }
  },
  "20060001": {
    "id": "20060001",
    "ShowId": "1009",
    "translation": {
      "x": -469.225,
      "y": -383.621,
      "z": 0
    }
  },
  "20026001": {
    "id": "20026001",
    "ShowId": "1004",
    "translation": {
      "x": -400.225,
      "y": -323.621,
      "z": 0
    }
  },
  "300009004": {
    "id": "300009004",
    "ShowId": "1005",
    "translation": {
      "x": -420.225,
      "y": -200.621,
      "z": 0
    }
  },
  "300010002": {
    "id": "300010002",
    "ShowId": "1007",
    "translation": {
      "x": -320.225,
      "y": -430.621,
      "z": 0
    }
  }
}