{
    "id": "1",
    "transform": {
        "translation": {
            "x": 952.8127,
            "y": 41.1433,
            "z": 87.5001
        },
        "rotation": {
            "x": 0.0,
            "y": 0.0,
            "z": -0.7071,
            "w": 0.7071
        },
        "scale3D": {
            "x": 1.0,
            "y": 1.0,
            "z": 1.0
        }
    },
    "name": "任务测试NPC",
    "description": "null",
    "kinds": "null",
    "author": "zheyuancao",
    "version": "null",
    "source": "npc_base_data@100001",
    "LuaID": 100001,
    "SuiteDir": "suite1",
    "UE5": {
        "UE5Comps": {
            "CollisionCylinder": {
                "RelativeLocation": {
                    "Type": "Vector",
                    "Value": {
                        "x": 952.8127,
                        "y": 41.1433,
                        "z": 87.5001
                    }
                }
            }
        }
    }
}